gdz/__init__.py
gdz/gdz.py
gdz/types/book.py
gdz/types/class_.py
gdz/types/edition.py
gdz/types/structure_entry.py
gdz/types/subject.py
gdz/types/task.py
gdz-0.1.5.dist-info/METADATA
gdz-0.1.5.dist-info/WHEEL
gdz-0.1.5.dist-info/top_level.txt
gdz-0.1.5.dist-info/RECORD
