Metadata-Version: 2.1
Name: gdz
Version: 0.1.5
Summary: Враппер API приложения ГДЗ: мой решебник (gdz.ru)
Home-page: https://github.com/crinny/gdz
Author: crinny
Author-email: 
License: MIT
Platform: UNKNOWN
Classifier: License :: OSI Approved :: MIT License
Classifier: Programming Language :: Python
Classifier: Programming Language :: Python :: 3
Classifier: Programming Language :: Python :: 3.6
Requires-Python: >=3.6.0
Requires-Dist: requests
Requires-Dist: pydantic
